liker.py
liker-0.0.4.dist-info/LICENSE
liker-0.0.4.dist-info/METADATA
liker-0.0.4.dist-info/WHEEL
liker-0.0.4.dist-info/top_level.txt
liker-0.0.4.dist-info/RECORD
