Metadata-Version: 2.1
Name: liker
Version: 0.0.4
Summary: functions that mimic R
Home-page: https://github.com/kwhkim
Author: kwhkim
Author-email: kwonhyun.kim@gmail.com
License: UNKNOWN
Project-URL: Bug Tracker, https://github.com/kwhkim
Platform: UNKNOWN
Classifier: Programming Language :: Python :: 3
Classifier: Operating System :: OS Independent
License-File: LICENSE
